{
  "id": 29331,
  "type": "tv",
  "title": "The Lone Ranger",
  "releaseDate": "1980-09-13",
  "posterImage": "https://static.tvmaze.com/uploads/images/original_untouched/116/292291.jpg",
  "backdropImage": "https://static.tvmaze.com/uploads/images/original_untouched/116/292291.jpg",
  "overview": "With one jaunty call, Hi-Yo, Silver!, Filmation's Lone Ranger rode into Saturday mornings. The Lone Ranger solidified his role as Americas favorite hero of the Wild West. Mounted atop the mighty horse, Silver, The Lone Ranger remains a steadfast symbol for truth and justice.",
  "score": null,
  "genres": [
    "Western"
  ],
  "screenshots": [],
  "systemRequirements": null
}