{
  "id": 27099,
  "type": "tv",
  "title": "Scared Famous",
  "releaseDate": "2017-10-23",
  "posterImage": "https://static.tvmaze.com/uploads/images/original_untouched/365/912658.jpg",
  "backdropImage": "https://static.tvmaze.com/uploads/images/original_untouched/365/912658.jpg",
  "overview": "Scared Famous is the frightening and hilarious tale of ten celebs who have bravely agreed to move into one of the spookiest mansions in America. Over eight episodes, they face terror and chilling challenges inspired by the iconic movies that make you scream. In this reality fright fest, ten famous people will move in, but only one will make it out alive.",
  "score": null,
  "genres": [
    "Comedy",
    "Horror",
    "Mystery"
  ],
  "screenshots": [],
  "systemRequirements": null
}