{
  "id": 35260,
  "type": "tv",
  "title": "Un Paso Adelante",
  "releaseDate": "2002-01-08",
  "posterImage": "https://static.tvmaze.com/uploads/images/original_untouched/148/371034.jpg",
  "backdropImage": "https://static.tvmaze.com/uploads/images/original_untouched/148/371034.jpg",
  "overview": "Un Paso Adelante is a Spanish version of the American 1980's TV series Fame. The show focuses on the professors and the students of \"Carmen Arranz\", one of the most prestigious art schools in Spain. The school is located in Madrid. The story follows Lola, Pedro, Rober, Jero, Ingrid, Silvia and Marta. They want to be successful singers, dancers and actors but they learn as they go along that the path to fame is not an easy one.",
  "score": null,
  "genres": [
    "Drama",
    "Comedy",
    "Music"
  ],
  "screenshots": [],
  "systemRequirements": null
}