{
  "id": 33042,
  "type": "tv",
  "title": "The Commander",
  "releaseDate": "2003-02-16",
  "posterImage": "https://static.tvmaze.com/uploads/images/original_untouched/140/350501.jpg",
  "backdropImage": "https://static.tvmaze.com/uploads/images/original_untouched/140/350501.jpg",
  "overview": "There are only four female commanders in the Metropolitan Police and only one of them specialises in murder. The Commander follows Commander Clare Blake of the homicide dIvision, whose team consists of the sinister D.C.I. Hedges, who is against her from the beginning.",
  "score": null,
  "genres": [
    "Drama",
    "Crime"
  ],
  "screenshots": [],
  "systemRequirements": null
}