{
  "id": 35084,
  "type": "tv",
  "title": "Mira lo que has hecho",
  "releaseDate": "2018-02-23",
  "posterImage": "https://static.tvmaze.com/uploads/images/original_untouched/146/367387.jpg",
  "backdropImage": "https://static.tvmaze.com/uploads/images/original_untouched/146/367387.jpg",
  "overview": "Set in Barcelona, tells the real story of Berto, a well-known Spanish comedian, when he becomes the terrified father of Lucas, with Sandra, his partner.",
  "score": null,
  "genres": [
    "Comedy"
  ],
  "screenshots": [],
  "systemRequirements": null
}