{
  "id": 38089,
  "type": "tv",
  "title": "Rojst",
  "releaseDate": "2018-08-19",
  "posterImage": "https://static.tvmaze.com/uploads/images/original_untouched/337/843613.jpg",
  "backdropImage": "https://static.tvmaze.com/uploads/images/original_untouched/337/843613.jpg",
  "overview": "The town is shocked with a brutal double murder. A small double murder shakes the town. \"Kurier\", the local newspaper, hands over this matter to an experienced journalist, Witold Wanycz. At the same time, he learns about the mysterious suicide of two teenagers. Together with Piotr, a young journalist, they begin their own investigation.",
  "score": 60,
  "genres": [
    "Drama",
    "Crime",
    "Thriller"
  ],
  "screenshots": [],
  "systemRequirements": null
}