{
  "id": 30184,
  "type": "tv",
  "title": "Sunny Day",
  "releaseDate": "2017-06-10",
  "posterImage": "https://static.tvmaze.com/uploads/images/original_untouched/119/298728.jpg",
  "backdropImage": "https://static.tvmaze.com/uploads/images/original_untouched/119/298728.jpg",
  "overview": "Sunny Day is a musical comedy animated series that features a hairstylist and a salon-owning entrepreneur named Sunny. With the help of her best friends, Blair, Rox and her adorable pup, Doodle, Sunny can solve any problem through determination, self-expression and a positive attitude. Above all, Sunny always uses her styling skills in creative ways to be a true leader and inspires individuality in every preschooler.",
  "score": null,
  "genres": [
    "Comedy",
    "Children",
    "Music"
  ],
  "screenshots": [],
  "systemRequirements": null
}