{
  "id": 37640,
  "type": "tv",
  "title": "Deka Wanko",
  "releaseDate": "2011-01-15",
  "posterImage": "https://static.tvmaze.com/uploads/images/original_untouched/160/401242.jpg",
  "backdropImage": "https://static.tvmaze.com/uploads/images/original_untouched/160/401242.jpg",
  "overview": "The comedic series revolves around a rookie detective named Ichiko Hanamori, whose exceptional dog-like sense of smell is used to solve difficult cases, in addition to earning her the nickname of Deka Wanko.",
  "score": null,
  "genres": [
    "Comedy",
    "Mystery"
  ],
  "screenshots": [],
  "systemRequirements": null
}