{
  "id": 44894,
  "type": "tv",
  "title": "Famously Afraid",
  "releaseDate": "2019-11-05",
  "posterImage": "https://static.tvmaze.com/uploads/images/original_untouched/382/956131.jpg",
  "backdropImage": "https://static.tvmaze.com/uploads/images/original_untouched/382/956131.jpg",
  "overview": "Celebrities reveal their terrifying true tales of encounters with the supernatural and unexplained—from hauntings to UFO sightings, to demonic possessions and beyond.",
  "score": null,
  "genres": [
    "Supernatural"
  ],
  "screenshots": [],
  "systemRequirements": null
}