{
  "id": 45558,
  "type": "tv",
  "title": "Love Journey",
  "releaseDate": "2019-04-20",
  "posterImage": "https://static.tvmaze.com/uploads/images/original_untouched/233/582552.jpg",
  "backdropImage": "https://static.tvmaze.com/uploads/images/original_untouched/233/582552.jpg",
  "overview": "A white-collar worker and a detective become embroiled in an elaborate mystery when a famous painting gets linked to an international drug smuggling enterprise.",
  "score": null,
  "genres": [
    "Drama",
    "Crime",
    "Romance"
  ],
  "screenshots": [],
  "systemRequirements": null
}