{
  "id": 42373,
  "type": "tv",
  "title": "Casanova",
  "releaseDate": "1971-11-16",
  "posterImage": "https://static.tvmaze.com/uploads/images/original_untouched/200/500062.jpg",
  "backdropImage": "https://static.tvmaze.com/uploads/images/original_untouched/200/500062.jpg",
  "overview": "Dennis Potter finds a contemporary relevance to the adventures of 17th-century Italian libertine Giacoma Casanova in a six-part series formed around Casanova's 1755 imprisonment.",
  "score": null,
  "genres": [
    "Drama"
  ],
  "screenshots": [],
  "systemRequirements": null
}