{
  "id": 40324,
  "type": "tv",
  "title": "Beyond the Unknown",
  "releaseDate": "2019-01-02",
  "posterImage": "https://static.tvmaze.com/uploads/images/original_untouched/403/1009595.jpg",
  "backdropImage": "https://static.tvmaze.com/uploads/images/original_untouched/403/1009595.jpg",
  "overview": "Don Wildman combs through the vaults of the world's most prestigious institutions to unearth extraordinary artifacts with captivating, revealing and shocking mysteries that challenge our beliefs and defy expectations.",
  "score": 42,
  "genres": [
    "Mystery",
    "Supernatural"
  ],
  "screenshots": [],
  "systemRequirements": null
}