{
  "id": 45553,
  "type": "tv",
  "title": "Yes Boss",
  "releaseDate": "1999-04-23",
  "posterImage": "https://static.tvmaze.com/uploads/images/original_untouched/518/1296176.jpg",
  "backdropImage": "https://static.tvmaze.com/uploads/images/original_untouched/518/1296176.jpg",
  "overview": "Meera and Mohan Srivastava are married and working in the same office. They have not disclosed their relationship to their boss Vinod Verma, who does not miss any chance of flirting with Meera. Mohan hates it and spends most of his time protecting his wife from Mr. Verma.",
  "score": null,
  "genres": [
    "Drama",
    "Comedy"
  ],
  "screenshots": [],
  "systemRequirements": null
}