{
  "id": 43278,
  "type": "tv",
  "title": "Vegas 24/7",
  "releaseDate": "2019-08-08",
  "posterImage": "https://static.tvmaze.com/uploads/images/original_untouched/209/523605.jpg",
  "backdropImage": "https://static.tvmaze.com/uploads/images/original_untouched/209/523605.jpg",
  "overview": "Documentary meeting some of the characters and hearing the stories that make the gambling capital of Las Vegas one of the most fun-filled cities on Earth.",
  "score": null,
  "genres": [],
  "screenshots": [],
  "systemRequirements": null
}