{
  "id": 50225,
  "type": "tv",
  "title": "Everything She Ever Wanted",
  "releaseDate": "2009-11-14",
  "posterImage": "https://static.tvmaze.com/uploads/images/original_untouched/384/961970.jpg",
  "backdropImage": "https://static.tvmaze.com/uploads/images/original_untouched/384/961970.jpg",
  "overview": "College dropout Tom Allanson is an embarrassing loser in the eyes of his father, reputed Savannah top lawyer Walter, who even sides with his first wife after their divorce sos he gets custody of the children. Yet handsome, popular, easy-going Tom is his vixen second wife Pat's dream prince, especially after she seduces him to buy her Monticello dream house, albeit beyond their means, and gets Walter's father George, who sold his house to care for his terminal wife, to pay half and move into a wing. After pat accuses Walter, probably falsely, of sexual abuse, he gets Tom fired without any prospect of another job, ans is shortly after shot at home. Tom's best friend, a cop, reluctantly acts as crown witness in his murder trial. Pat, who made him turn down a plea bargain, can't afford the estate much longer and resorts to extreme measures.  ",
  "score": null,
  "genres": [],
  "screenshots": [],
  "systemRequirements": null
}