{
  "id": 59555,
  "type": "tv",
  "title": "SciShow Kids",
  "releaseDate": "2015-03-09",
  "posterImage": "https://static.tvmaze.com/uploads/images/original_untouched/384/961633.jpg",
  "backdropImage": "https://static.tvmaze.com/uploads/images/original_untouched/384/961633.jpg",
  "overview": "SciShow Kids explores all those curious topics that make us ask \"why?\" Whether conducting experiments, researching new questions, or talking with experts, there's always something new to discover with SciShow Kids, no matter what your age!",
  "score": null,
  "genres": [],
  "screenshots": [],
  "systemRequirements": null
}