{
  "id": 52780,
  "type": "tv",
  "title": "Mermaid Prince",
  "releaseDate": "2020-11-25",
  "posterImage": "https://static.tvmaze.com/uploads/images/original_untouched/291/729458.jpg",
  "backdropImage": "https://static.tvmaze.com/uploads/images/original_untouched/291/729458.jpg",
  "overview": "‎Shen Moo, has no idea what adventures she will face. Beauty, is one of the best observers of Internet resources, but soon, in her head creeps the idea that in the universe there are mermaids. It's hard to believe, but for some reason, she can't get it out of her mind. Soon, she will have to take responsibility to prove their existence, otherwise, the dispute with the professor will turn out to be a real failure for the heroine. Together with the rescue team, they went to help the victims in The Xine Bay. Meet Ahn Xin - an athlete, will turn her reality. Unbelievable, but the guy is perceived as a mermaid. Of course, Mu Xin liked it madly, because she found a key witness and will be able to insist on her own. However, the mermaid man does his best to avoid revealing his real world.‎",
  "score": null,
  "genres": [
    "Comedy",
    "Fantasy",
    "Romance"
  ],
  "screenshots": [],
  "systemRequirements": null
}