{
  "id": 55840,
  "type": "tv",
  "title": "A Luv Tale",
  "releaseDate": "2021-06-03",
  "posterImage": "https://static.tvmaze.com/uploads/images/original_untouched/389/974019.jpg",
  "backdropImage": "https://static.tvmaze.com/uploads/images/original_untouched/389/974019.jpg",
  "overview": "Taylor, Candice, Aklia, and Tammy's journeys as queer women may look different, but as they cross paths in Harlem, they help each other untangle life's complexities and be their authentic selves.",
  "score": null,
  "genres": [
    "Drama",
    "Romance"
  ],
  "screenshots": [],
  "systemRequirements": null
}