{
  "id": 59338,
  "type": "tv",
  "title": "Ghost Doctor",
  "releaseDate": "2022-01-03",
  "posterImage": "https://static.tvmaze.com/uploads/images/original_untouched/382/956011.jpg",
  "backdropImage": "https://static.tvmaze.com/uploads/images/original_untouched/382/956011.jpg",
  "overview": "Cha Young Min is a genius doctor, but he is arrogant and selfish. One day, he gets involved in an unexpected case. Due to the unexpected case, his spirit possesses another doctor's body. These two doctors are complete opposites, with opposite personalities and medical abilities.",
  "score": 78,
  "genres": [
    "Fantasy",
    "Medical"
  ],
  "screenshots": [],
  "systemRequirements": null
}