{
  "id": 55493,
  "type": "tv",
  "title": "Xiang Wang De Sheng Huo",
  "releaseDate": "2017-01-15",
  "posterImage": "https://static.tvmaze.com/uploads/images/original_untouched/320/801103.jpg",
  "backdropImage": "https://static.tvmaze.com/uploads/images/original_untouched/320/801103.jpg",
  "overview": "It features a core cast of celebrities living on a farm, with new guests each day to help with the work. In each episode, the guests call ahead to order a dish they want, and the hosts attempt to make it. The guests help throughout the day and spend the night, leaving in the next episode. This season, regular MCs included He Jiong, Huang Lei and Henry Lau.",
  "score": null,
  "genres": [],
  "screenshots": [],
  "systemRequirements": null
}