{
  "id": 54954,
  "type": "tv",
  "title": "Nødt eller Sannhet",
  "releaseDate": "2021-04-19",
  "posterImage": "https://static.tvmaze.com/uploads/images/original_untouched/379/948817.jpg",
  "backdropImage": "https://static.tvmaze.com/uploads/images/original_untouched/379/948817.jpg",
  "overview": "The story of the first great love, a friendship that means more than anything else and the obsessions that no one must know about.",
  "score": null,
  "genres": [
    "Drama",
    "Children"
  ],
  "screenshots": [],
  "systemRequirements": null
}