{
  "id": 50088,
  "type": "tv",
  "title": "Welcome to the Blumhouse",
  "releaseDate": "2020-10-06",
  "posterImage": "https://static.tvmaze.com/uploads/images/original_untouched/350/875473.jpg",
  "backdropImage": "https://static.tvmaze.com/uploads/images/original_untouched/350/875473.jpg",
  "overview": "Welcome to the Blumhouse is an anthology of eight genre movies produced by Jason Blum's Blumhouse Television and Amazon Studios.",
  "score": 63,
  "genres": [
    "Horror"
  ],
  "screenshots": [],
  "systemRequirements": null
}