{
  "id": 51074,
  "type": "tv",
  "title": "Every Woman Knows a Secret",
  "releaseDate": "1999-03-18",
  "posterImage": "https://static.tvmaze.com/uploads/images/original_untouched/277/693094.jpg",
  "backdropImage": "https://static.tvmaze.com/uploads/images/original_untouched/277/693094.jpg",
  "overview": "When 40-something divorcee Jess's son is killed in a drink-drive road crash, she finds comfort with the driver of the car.",
  "score": null,
  "genres": [
    "Drama"
  ],
  "screenshots": [],
  "systemRequirements": null
}