{
  "id": 59849,
  "type": "tv",
  "title": "Mullaen og Meling",
  "releaseDate": "2022-01-10",
  "posterImage": "https://static.tvmaze.com/uploads/images/original_untouched/388/972308.jpg",
  "backdropImage": "https://static.tvmaze.com/uploads/images/original_untouched/388/972308.jpg",
  "overview": "He was a danger to the security of the kingdom, yet he lived among us for 30 years. See the story of a hated mullah and his faithful lawyer.",
  "score": null,
  "genres": [
    "Crime"
  ],
  "screenshots": [],
  "systemRequirements": null
}