{
  "id": 55222,
  "type": "tv",
  "title": "Галыгин.Ру",
  "releaseDate": "2010-02-13",
  "posterImage": "https://static.tvmaze.com/uploads/images/original_untouched/315/789309.jpg",
  "backdropImage": "https://static.tvmaze.com/uploads/images/original_untouched/315/789309.jpg",
  "overview": "The main character - Vadik, works in a stand-up comedy show and conducts corporate events. Each episode is a separate story that takes place with Vadik and his friends, whose life is full of funny situations and unexpected adventures.\nThe show combines incompatible things: sitcom, \"stand up comedy\" and reality show. Each episode is preceded by an epigraph that briefly and succinctly describes its content.",
  "score": null,
  "genres": [
    "Comedy"
  ],
  "screenshots": [],
  "systemRequirements": null
}