{
  "id": 57899,
  "type": "tv",
  "title": "The Mating Game",
  "releaseDate": "2021-10-03",
  "posterImage": "https://static.tvmaze.com/uploads/images/original_untouched/365/914733.jpg",
  "backdropImage": "https://static.tvmaze.com/uploads/images/original_untouched/365/914733.jpg",
  "overview": "Series exploring the lengths that animals go to in search of a mate, featuring footage of dancing, fighting and even deceiving potential partners.",
  "score": 80,
  "genres": [],
  "screenshots": [],
  "systemRequirements": null
}