{
  "id": 68685,
  "type": "tv",
  "title": "Brennpunkt: Cyberkriger",
  "releaseDate": "2023-05-10",
  "posterImage": "https://static.tvmaze.com/uploads/images/original_untouched/516/1292233.jpg",
  "backdropImage": "https://static.tvmaze.com/uploads/images/original_untouched/516/1292233.jpg",
  "overview": "Hidden behind keyboards and pseudonyms, they defy laws and put themselves and others in danger - all to stop Putin in the war against Ukraine.",
  "score": null,
  "genres": [],
  "screenshots": [],
  "systemRequirements": null
}