{
  "id": 65288,
  "type": "tv",
  "title": "De Oranjewinter",
  "releaseDate": "2022-11-20",
  "posterImage": "https://static.tvmaze.com/uploads/images/original_untouched/551/1378236.jpg",
  "backdropImage": "https://static.tvmaze.com/uploads/images/original_untouched/551/1378236.jpg",
  "overview": "Wilfred Genee, Johan Derksen and René van der Gijp discuss all developments surrounding the World Cup in Qatar with various guests from the studio in Hilversum.",
  "score": null,
  "genres": [],
  "screenshots": [],
  "systemRequirements": null
}