{
  "id": 64845,
  "type": "tv",
  "title": "Shards of Her",
  "releaseDate": "2022-10-28",
  "posterImage": "https://static.tvmaze.com/uploads/images/original_untouched/428/1070716.jpg",
  "backdropImage": "https://static.tvmaze.com/uploads/images/original_untouched/428/1070716.jpg",
  "overview": "Waking up from a coma, an accomplished headhunter finds herself in an alternate reality where she has to revisit an excruciating childhood trauma.",
  "score": null,
  "genres": [
    "Crime",
    "Thriller",
    "Mystery"
  ],
  "screenshots": [],
  "systemRequirements": null
}