{
  "id": 67668,
  "type": "tv",
  "title": "Meet With Two Souls",
  "releaseDate": "2023-03-23",
  "posterImage": "https://static.tvmaze.com/uploads/images/original_untouched/453/1134007.jpg",
  "backdropImage": "https://static.tvmaze.com/uploads/images/original_untouched/453/1134007.jpg",
  "overview": "The naive and innocent wealthy young lady, Luo Xuan, discovered that her perfect husband, Yan Zhi Jing, had betrayed her and even wanted to take over her family's inheritance. She chose to join forces with her childhood friend, Min Xi, to eliminate the enemy and expose the conspiracy between Yan Zhi Jing and his mistress, Bai Jia Jia.",
  "score": null,
  "genres": [
    "Drama",
    "Romance"
  ],
  "screenshots": [],
  "systemRequirements": null
}