{
  "id": 675,
  "type": "tv",
  "title": "Ancient Aliens (New Episode)",
  "releaseDate": "2025-09-12",
  "posterImage": "https://static.tvmaze.com/uploads/images/original_untouched/561/1403626.jpg",
  "backdropImage": "https://static.tvmaze.com/uploads/images/original_untouched/561/1403626.jpg",
  "overview": "Ancient Aliens explores the controversial theory that extraterrestrials have visited Earth for millions of years. From the age of the dinosaurs to ancient Egypt, from early cave drawings to continued mass sightings in the US, each episode in this hit History series gives historic depth to the questions, speculations, provocative controversies, first-hand accounts and grounded theories surrounding this age old debate. Did intelligent beings from outer space visit Earth thousands of years ago?",
  "score": 65,
  "genres": [],
  "screenshots": [],
  "systemRequirements": null
}