{
  "id": 60546,
  "type": "tv",
  "title": "Son Nefesime Kadar",
  "releaseDate": "2022-02-23",
  "posterImage": "https://static.tvmaze.com/uploads/images/original_untouched/396/992075.jpg",
  "backdropImage": "https://static.tvmaze.com/uploads/images/original_untouched/396/992075.jpg",
  "overview": "Son Nefesime Kadar tells the story of a woman who works as a commissioner in a small town, whose whole world is turned upside down when the man she thinks is responsible for her daughter's death is released from prison.",
  "score": null,
  "genres": [
    "Drama",
    "Crime"
  ],
  "screenshots": [],
  "systemRequirements": null
}