{
  "id": 70812,
  "type": "tv",
  "title": "Safir",
  "releaseDate": "2023-09-04",
  "posterImage": "https://static.tvmaze.com/uploads/images/original_untouched/474/1185427.jpg",
  "backdropImage": "https://static.tvmaze.com/uploads/images/original_untouched/474/1185427.jpg",
  "overview": "Gülsoys, one of the leading families of Cappadocia, came together after Ateş returned from America. Ateş did not bow to the overwhelming authority of his grandfather Ömer and left the house. After many years, at the request of his mother Gülfem, he returned to his home with his brothers Yaman and Okan to take over and expand the family business from his grandfather. Now is the time to unite for Ateş, Yaman and Okan. After his brother's return, Yaman decides to propose to his lover Feraye. When Yaman was a child, he secretly bought the family heirloom Sapphire ring from his mother and proposed to Feraye. While Feraye and Yaman are counting the days to get married, confessing their great love by risking everything, a tragedy upsets all the balances. Feraye and Yaman are about to get lost on dangerous roads full of love, passion, revenge and tyranny. Ateş will both win new enemies and confront his brothers with the radical decisions he takes to protect everyone he loves and his family.",
  "score": 55,
  "genres": [
    "Drama",
    "Romance"
  ],
  "screenshots": [],
  "systemRequirements": null
}