{
  "id": 73243,
  "type": "tv",
  "title": "Bienvenue chez les Ronks!",
  "releaseDate": "2017-02-06",
  "posterImage": "https://static.tvmaze.com/uploads/images/original_untouched/491/1227667.jpg",
  "backdropImage": "https://static.tvmaze.com/uploads/images/original_untouched/491/1227667.jpg",
  "overview": "Flash, a refined alien, is sent to Earth in order to get the Ronks, a tribe of Neanderthals, to evolve. But are they ready for (r)evolution?",
  "score": null,
  "genres": [
    "Children",
    "Science-Fiction"
  ],
  "screenshots": [],
  "systemRequirements": null
}