{
  "id": 76708,
  "type": "tv",
  "title": "Made in Norway",
  "releaseDate": "2017-04-22",
  "posterImage": "https://static.tvmaze.com/uploads/images/original_untouched/517/1294613.jpg",
  "backdropImage": "https://static.tvmaze.com/uploads/images/original_untouched/517/1294613.jpg",
  "overview": "All over Norway there are entrepreneurs who are working hard to make their dreams come true. Who has what it takes? And how much are they willing to sacrifice?",
  "score": null,
  "genres": [],
  "screenshots": [],
  "systemRequirements": null
}