{
  "id": 74697,
  "type": "tv",
  "title": "Dino & the Egg Hunt",
  "releaseDate": "2021-01-04",
  "posterImage": "https://static.tvmaze.com/uploads/images/original_untouched/504/1261026.jpg",
  "backdropImage": "https://static.tvmaze.com/uploads/images/original_untouched/504/1261026.jpg",
  "overview": "BabyTV is going back in time to the days of the dinosaurs where two dinosaur eggs have disappeared from the baby dinosaur kindergarten. In each episode our heroes follow the egg trail on a mission to find the eggs and return them safely to the kindergarten.",
  "score": null,
  "genres": [
    "Children"
  ],
  "screenshots": [],
  "systemRequirements": null
}