{
  "id": 83241,
  "type": "tv",
  "title": "Otherwords",
  "releaseDate": "2021-03-24",
  "posterImage": "https://static.tvmaze.com/uploads/images/original_untouched/559/1399399.jpg",
  "backdropImage": "https://static.tvmaze.com/uploads/images/original_untouched/559/1399399.jpg",
  "overview": "Otherwords digs deep into this quintessential human trait of language and finds the fascinating, thought-provoking, and funny stories behind the words and sounds we take for granted. Incorporating the fields of biology, history, cultural studies, literature and more, linguistics has something for everyone and offers a unique perspective on what it means to be human",
  "score": null,
  "genres": [
    "History"
  ],
  "screenshots": [],
  "systemRequirements": null
}